ctrace/__init__.py
ctrace/constants.py
ctrace/data.py
ctrace/enums.py
climate_trace-0.4.0.dist-info/LICENSE
climate_trace-0.4.0.dist-info/METADATA
climate_trace-0.4.0.dist-info/WHEEL
climate_trace-0.4.0.dist-info/RECORD
